AUTHORS
COPYING
INSTALL
LICENSE
MANIFEST.in
README.rst
setup.cfg
setup.py
bin/tomahawk
bin/tomahawk-rsync
docs/en/_tomahawk-rsync_description.rst
docs/en/_tomahawk_description.rst
docs/en/_tomahawk_env_vars.rst
docs/en/changes.rst
docs/en/index.rst
docs/en/install.rst
docs/en/recipes.rst
docs/en/tomahawk-rsync.rst
docs/en/tomahawk.rst
man/man1/tomahawk-rsync.1
man/man1/tomahawk.1
tomahawk/__init__.py
tomahawk/base.py
tomahawk/bootstrap.py
tomahawk/color.py
tomahawk/command.py
tomahawk/constants.py
tomahawk/expect.py
tomahawk/log.py
tomahawk/rsync.py
tomahawk/utils.py
tomahawk.egg-info/PKG-INFO
tomahawk.egg-info/SOURCES.txt
tomahawk.egg-info/dependency_links.txt
tomahawk.egg-info/not-zip-safe
tomahawk.egg-info/requires.txt
tomahawk.egg-info/top_level.txt